syphon/__init__.py
syphon/client.py
syphon/server.py
syphon/server_directory.py
syphon/types.py
syphon/libs/Syphon.framework/Syphon
syphon/libs/Syphon.framework/Headers/Syphon.h
syphon/libs/Syphon.framework/Headers/SyphonClient.h
syphon/libs/Syphon.framework/Headers/SyphonClientBase.h
syphon/libs/Syphon.framework/Headers/SyphonImage.h
syphon/libs/Syphon.framework/Headers/SyphonImageBase.h
syphon/libs/Syphon.framework/Headers/SyphonMetalClient.h
syphon/libs/Syphon.framework/Headers/SyphonMetalServer.h
syphon/libs/Syphon.framework/Headers/SyphonOpenGLClient.h
syphon/libs/Syphon.framework/Headers/SyphonOpenGLImage.h
syphon/libs/Syphon.framework/Headers/SyphonOpenGLServer.h
syphon/libs/Syphon.framework/Headers/SyphonServer.h
syphon/libs/Syphon.framework/Headers/SyphonServerBase.h
syphon/libs/Syphon.framework/Headers/SyphonServerDirectory.h
syphon/libs/Syphon.framework/Headers/SyphonSubclassing.h
syphon/libs/Syphon.framework/Modules/module.modulemap
syphon/libs/Syphon.framework/Resources/Info.plist
syphon/libs/Syphon.framework/Resources/default.metallib
syphon/libs/Syphon.framework/Resources/en.lproj/InfoPlist.strings
syphon/libs/Syphon.framework/Versions/A/Syphon
syphon/libs/Syphon.framework/Versions/A/Headers/Syphon.h
syphon/libs/Syphon.framework/Versions/A/Headers/SyphonClient.h
syphon/libs/Syphon.framework/Versions/A/Headers/SyphonClientBase.h
syphon/libs/Syphon.framework/Versions/A/Headers/SyphonImage.h
syphon/libs/Syphon.framework/Versions/A/Headers/SyphonImageBase.h
syphon/libs/Syphon.framework/Versions/A/Headers/SyphonMetalClient.h
syphon/libs/Syphon.framework/Versions/A/Headers/SyphonMetalServer.h
syphon/libs/Syphon.framework/Versions/A/Headers/SyphonOpenGLClient.h
syphon/libs/Syphon.framework/Versions/A/Headers/SyphonOpenGLImage.h
syphon/libs/Syphon.framework/Versions/A/Headers/SyphonOpenGLServer.h
syphon/libs/Syphon.framework/Versions/A/Headers/SyphonServer.h
syphon/libs/Syphon.framework/Versions/A/Headers/SyphonServerBase.h
syphon_python-0.1.1.dist-info/LICENSE
syphon_python-0.1.1.dist-info/METADATA
syphon_python-0.1.1.dist-info/WHEEL
syphon_python-0.1.1.dist-info/top_level.txt
syphon_python-0.1.1.dist-info/RECORD
