Metadata-Version: 2.1
Name: syphon-python
Version: 0.1.1
Summary: Python wrapper for the GPU texture sharing framework Syphon.
Home-page: https://github.com/cansik/syphon-python
Author: Florian Bruggisser
Author-email: github@broox.ch
License: MIT License
Platform: UNKNOWN
License-File: LICENSE
Requires-Dist: pyobjc-core ~=10.1
Requires-Dist: pyobjc-framework-metal ~=10.1
Requires-Dist: pyobjc-framework-cocoa ~=10.1
Requires-Dist: pyopengl ~=3.1.7
